qftools/__init__.py
qftools/date/__init__.py
qftools/date/calendar.py
qftools/date/datemath.py
qftools/date/daycount.py
qftools/date/frequency.py
qftools/date/roll.py
qftools/date/tenor.py
qftools-0.1.1.dist-info/LICENSE
qftools-0.1.1.dist-info/METADATA
qftools-0.1.1.dist-info/WHEEL
qftools-0.1.1.dist-info/RECORD
