Metadata-Version: 2.3
Name: qftools
Version: 0.1.1
Summary: Python Toolkit for Quantitative Finance
License: MIT
Author: Reece Miao
Author-email: reece.miao@outlook.com
Requires-Python: >=3.12
Classifier: License :: OSI Approved :: MIT License
Classifier: Programming Language :: Python :: 3
Classifier: Programming Language :: Python :: 3.12
Classifier: Programming Language :: Python :: 3.13
Requires-Dist: numpy (>=2.2.1,<3.0.0)
